pyaegis/__init__.py
pyaegis/_aegis_ffi.abi3.so
pyaegis/aegis.py
pyaegis/py.typed
pyaegis-0.1.0.dist-info/licenses/LICENSE
pyaegis-0.1.0.dist-info/METADATA
pyaegis-0.1.0.dist-info/WHEEL
pyaegis-0.1.0.dist-info/top_level.txt
pyaegis-0.1.0.dist-info/RECORD
