Metadata-Version: 2.4
Name: pyaegis
Version: 0.1.0
Summary: Python bindings for libaegis - high-performance AEGIS authenticated encryption
Author-email: Frank Denis <github@pureftpd.org>
License: MIT
Project-URL: Homepage, https://github.com/aegis-aead/pyaegis
Project-URL: Repository, https://github.com/aegis-aead/pyaegis
Project-URL: Issues, https://github.com/aegis-aead/pyaegis/issues
Project-URL: Changelog, https://github.com/aegis-aead/pyaegis/blob/main/CHANGELOG.md
Keywords: aegis,encryption,authenticated-encryption,aead,cryptography,cffi,security,crypto
Classifier: Development Status :: 4 - Beta
Classifier: Intended Audience :: Developers
Classifier: License :: OSI Approved :: MIT License
Classifier: Programming Language :: Python :: 3
Classifier: Programming Language :: Python :: 3.11
Classifier: Programming Language :: Python :: 3.12
Classifier: Programming Language :: Python :: 3.13
Classifier: Programming Language :: C
Classifier: Topic :: Security :: Cryptography
Classifier: Topic :: Software Development :: Libraries :: Python Modules
Classifier: Operating System :: OS Independent
Classifier: Typing :: Typed
Requires-Python: >=3.11
License-File: LICENSE
Requires-Dist: cffi>=2.0.0
Provides-Extra: dev
Requires-Dist: pytest>=8.4.2; extra == "dev"
Requires-Dist: pytest-cov>=7.0.0; extra == "dev"
Requires-Dist: build>=1.3.0; extra == "dev"
Requires-Dist: twine>=6.2.0; extra == "dev"
Requires-Dist: ruff>=0.14.2; extra == "dev"
Requires-Dist: mypy>=1.18.2; extra == "dev"
Requires-Dist: pre-commit>=4.3.0; extra == "dev"
Provides-Extra: test
Requires-Dist: pytest>=8.4.2; extra == "test"
Requires-Dist: pytest-cov>=7.0.0; extra == "test"
Dynamic: license-file
